luno_python/__init__.py
luno_python/base_client.py
luno_python/client.py
luno_python/error.py
luno_python-0.0.10.dist-info/LICENSE.txt
luno_python-0.0.10.dist-info/METADATA
luno_python-0.0.10.dist-info/WHEEL
luno_python-0.0.10.dist-info/top_level.txt
luno_python-0.0.10.dist-info/RECORD
