Metadata-Version: 2.1
Name: luno-python
Version: 0.0.10
Summary: A Luno API client for Python
Home-page: https://github.com/luno/luno-python
Download-URL: https://github.com/luno/luno-python/tarball/0.0.10
Author: Neil Garb
Author-email: neil@luno.com
License: MIT
Keywords: Luno API Bitcoin Ethereum
License-File: LICENSE.txt
Requires-Dist: requests (>=2.18.4)
Requires-Dist: six (>=1.11.0)
